supernodes/__init__.py
supernodes/nodes.py
supernodes/operations.py
supernodes-1.0.1.dist-info/LICENSE.md
supernodes-1.0.1.dist-info/METADATA
supernodes-1.0.1.dist-info/WHEEL
supernodes-1.0.1.dist-info/top_level.txt
supernodes-1.0.1.dist-info/RECORD
