Metadata-Version: 2.1
Name: supernodes
Version: 1.0.1
Summary: Creates tree data structures easily
Home-page: UNKNOWN
Author: Mubarak Almehairbi
License: UNKNOWN
Platform: UNKNOWN
Classifier: Programming Language :: Python :: 3
Classifier: License :: OSI Approved :: MIT License
Classifier: Operating System :: OS Independent
Requires-Python: >=3.6
License-File: LICENSE.md
Requires-Dist: pandas (>=1.4.2)
Requires-Dist: PyYAML (>=6.0)
